{"appId":"de.z11.roboyard","appShortcutName":"Roboyard","appDisplayName":"Roboyard","authorId":"Ruben Barkow-Kuder","releaseTagName":"","downloadUrls":{"1":{"installerType":"AndroidApkZip","asset":"","url":"https://github.com//https://github.com/Eastcoast-Laboratories/Roboyard/releases/download//"}},"install":{"win32":null,"winarm":null,"linux":null,"linuxArm64":null,"linuxArm7":null,"android":{"assetId":1}},"displayImages":[],"description":"Problem-solving game - find the optimal moves to move one robot to its target\nAn Android-based application like the board game \"Ricochet Robots ©\". It includes an artificial intelligence capable of solving the puzzles.\n\nA simple but challenging puzzle game.\n\nYou control four robots in a yard full of hedges, that block their way. The goal is to guide a particular robot to its destination. The robots move until they either hit a hedge or another robot.\n\nThe special feature of this app is the automatic solution finding algorithm, which can show you hints and also the optimal solution.\n\nCan you find the solution with the fewest moves?\n\nThis game is open source and shipped without adds. \n\nSource code: https://roboyard.z11.de/\n","repo":{"author":"","repo":"https://github.com/Eastcoast-Laboratories/Roboyard"},"version":"a9a62bcd8e2d783efce58fd17f6f0a5558560ec3f34a9f23d19d4e7a3b18849d","site":null,"source":"https://github.com/Eastcoast-Laboratories/Roboyard","license_or_tos":"GPL-3.0-only","resources":null,"verified":false}